<?xml version="1.0" encoding="UTF-8"?>
<ObjectDefinition>  <information>
    <allowLaunchOnFailedProcess>true</allowLaunchOnFailedProcess>
    <description>network connectivity orchestration for 5G and IOT</description>
    <displayField>service_id</displayField>
    <executionDetailsVisibility>5</executionDetailsVisibility>
    <executionMode>TRANSACTION</executionMode>
    <group>network</group>
    <icon>/images/eclipseIcons/page_obj.gif</icon>
    <name>Network Orchestration</name>
    <order>10000</order>
    <poolId>0</poolId>
    <readVariableVisibility>5</readVariableVisibility>
    <showDetailedServiceInstances>false</showDetailedServiceInstances>
    <showProcessExecConsole>false</showProcessExecConsole>
    <showVariables>false</showVariables>
    <visibility>5</visibility>
  </information>  <variables frozen="0">
    <variable displayName="Interfaces" displayOrder="0" maxLength="100" name="params.interfaces.0.name" numberOfRowMax="0" startIncrement="0" tableSizeFix="false" type="String"/>
    <variable default="hundredgigabitethernet 3/1" displayName="Interface" displayOrder="1" editable="false" maxLength="100" name="params.interface" numberOfRowMax="0" startIncrement="0" tableSizeFix="false" type="String"/>
    <variable displayName="VLAN Id" displayOrder="2" editable="false" maxLength="100" name="params.subinterface" numberOfRowMax="0" startIncrement="0" tableSizeFix="false" type="Integer">
      <values>
        <value>1100</value>
      </values>
    </variable>
    <variable displayName="Customer Id" displayOrder="3" maxLength="100" name="params.customer_id" numberOfRowMax="0" startIncrement="0" tableSizeFix="false" type="Customer">
      <sections>
        <section>Add device</section>
      </sections>
    </variable>
    <variable default="RCP #1" displayName="Managed Device Name" displayOrder="4" editable="false" isMandatory="true" maxLength="100" name="params.managed_device_name" numberOfRowMax="0" startIncrement="0" tableSizeFix="false" type="String">
      <values>
        <value displayValue="RCP #4">RCP #4</value>
        <value displayValue="RCP #1">RCP #1</value>
      </values>
      <sections>
        <section>Add device</section>
      </sections>
    </variable>
    <variable displayName="Host" displayOrder="5" maxLength="100" name="params.device_ip_address" numberOfRowMax="0" selector="params.managed_device_name" startIncrement="0" tableSizeFix="false" type="Composite">
      <values>
        <value displayValue="133.69.35.21">133.69.35.21</value>
        <value displayValue="133.69.35.22">133.69.35.22</value>
      </values>
      <sections>
        <section>Add device</section>
      </sections>
      <behaviors>
        <behavior default="133.69.35.21" displayName="IP Address" displayOrder="0" editable="false" isMandatory="true" maxLength="100" name="params.device_ip_address" numberOfRowMax="0" selectorValue="RCP #1" startIncrement="0" tableSizeFix="false" type="IpAddress">
          <values>
            <value displayValue="133.69.35.21">133.69.35.21</value>
          </values>
        </behavior>
        <behavior default="133.69.35.22" displayName="IP Address" displayOrder="0" editable="false" isMandatory="true" maxLength="100" name="params.device_ip_address" numberOfRowMax="0" selectorValue="RCP #4" startIncrement="0" tableSizeFix="false" type="String">
          <values>
            <value displayValue="133.69.35.22">133.69.35.22</value>
          </values>
        </behavior>
      </behaviors>
    </variable>
    <variable default="my_login" displayName="Login" displayOrder="6" editable="false" maxLength="100" name="params.login" numberOfRowMax="0" startIncrement="0" tableSizeFix="false" type="String" visible="false">
      <sections>
        <section>Add device</section>
      </sections>
    </variable>
    <variable default="my_password" displayName="Password" displayOrder="7" editable="false" maxLength="100" name="params.password" numberOfRowMax="0" startIncrement="0" tableSizeFix="false" type="Password" visible="false">
      <sections>
        <section>Add device</section>
      </sections>
    </variable>
    <variable displayName="Password Admin" displayOrder="8" editable="false" maxLength="100" name="params.password_admin" numberOfRowMax="0" startIncrement="0" tableSizeFix="false" type="Password" visible="false">
      <sections>
        <section>Add device</section>
      </sections>
    </variable>
    <variable displayName="Device Id" displayOrder="9" editable="false" maxLength="100" name="params.device_id" numberOfRowMax="0" startIncrement="0" tableSizeFix="false" type="Device" visible="false">
      <sections>
        <section>Provision Device</section>
      </sections>
    </variable>
    <variable displayName="Device External Reference" displayOrder="10" editable="false" maxLength="100" name="params.device_external_reference" numberOfRowMax="0" startIncrement="0" tableSizeFix="false" type="String" visible="false">
      <sections>
        <section>Add device</section>
      </sections>
    </variable>
    <variable default="14020601" displayName="Manufacturer Id" displayOrder="11" editable="false" maxLength="100" name="params.manufacturer_id" numberOfRowMax="0" startIncrement="0" tableSizeFix="false" type="Integer" visible="false">
      <sections>
        <section>Add device</section>
      </sections>
    </variable>
    <variable default="14020601" displayName="Model Id" displayOrder="12" editable="false" maxLength="100" name="params.model_id" numberOfRowMax="0" startIncrement="0" tableSizeFix="false" type="Integer" visible="false">
      <sections>
        <section>Add device</section>
      </sections>
    </variable>
  </variables>  <example>    <content>
      <?php?>
    </content>  </example>
  <process name="Process/OpenMSA/Samples/Example_Usecases/05._Network_Orchestration/Alaxala/Process_VLAN_management">
    <visibility>5</visibility>
    <displayName>VLAN Management</displayName>
    <icon/>
    <poolId>0</poolId>
    <compensation/>
    <allowSchedule>false</allowSchedule>
    <type>CREATE</type>
  <task name="Task_Enter_Parameters.php">
      <processPath>/opt/fmc_repository/Process/OpenMSA/Samples/Example_Usecases/05._Network_Orchestration/Alaxala/Process_VLAN_management/Tasks/</processPath>
      <displayName>Enter Parameters</displayName>
    </task>
    <task name="/opt/fmc_repository/Process/Reference/MSActivator/Device/Task_msa_device_create.php">
      <processPath>/opt/fmc_repository/Process/OpenMSA/Samples/Example_Usecases/05._Network_Orchestration/Alaxala/Process_VLAN_management/Tasks/</processPath>
      <displayName>Add device</displayName>
    </task>
    <task name="/opt/fmc_repository/Process/Reference/MSActivator/Device/Task_msa_device_ping_check.php">
      <processPath/>
      <displayName>Test Conn</displayName>
    </task>
    <task name="/opt/fmc_repository/Process/Reference/MSActivator/Device/Task_mark_device_as_provisioned.php">
      <processPath/>
      <displayName>Provision Device</displayName>
    </task>
  </process>
  <process name="Process/OpenMSA/Samples/Example_Usecases/05._Network_Orchestration/Alaxala/Process_GET">
    <visibility>5</visibility>
    <displayName>VLAN Discovery</displayName>
    <icon/>
    <poolId>0</poolId>
    <compensation/>
    <allowSchedule>false</allowSchedule>
    <type>UPDATE</type>
    <task name="Task_GET.php">
      <processPath>/opt/fmc_repository/Process/OpenMSA/Samples/Example_Usecases/05._Network_Orchestration/Alaxala/Process_GET/Tasks/</processPath>
      <displayName>GET</displayName>
    </task>
  </process>
<process name="Process/OpenMSA/Samples/Example_Usecases/05._Network_Orchestration/Alaxala/Process_PUT">
    <visibility>5</visibility>
    <displayName>Create/Update Vlan</displayName>
    <icon/>
    <poolId>0</poolId>
    <compensation/>
    <allowSchedule>false</allowSchedule>
    <type>UPDATE</type>
    <task name="Task_PUT.php">
      <processPath>/opt/fmc_repository/Process/OpenMSA/Samples/Example_Usecases/05._Network_Orchestration/Alaxala/Process_PUT/Tasks/</processPath>
      <displayName>PUT</displayName>
    </task>
  </process>
  

<process name="Process/OpenMSA/Samples/Example_Usecases/05._Network_Orchestration/Alaxala/Process_delete">
    <visibility>5</visibility>
    <displayName>Delete Instance</displayName>
    <icon/>
    <poolId>0</poolId>
    <compensation/>
    <allowSchedule>false</allowSchedule>
    <type>DELETE</type>
  <task name="/opt/fmc_repository/Process/Reference/MSActivator/Device/Task_msa_device_delete.php">
      <processPath/>
      <displayName>Delete Device</displayName>
    </task>
  </process>
<process name="Process/OpenMSA/Samples/Example_Usecases/05._Network_Orchestration/Alaxala/Process_Del_VLAN">
    <visibility>5</visibility>
    <displayName>Remove VLAN</displayName>
    <icon/>
    <poolId>0</poolId>
    <compensation/>
    <allowSchedule>false</allowSchedule>
    <type>UPDATE</type>
    
  <task name="/opt/fmc_repository/Process/OpenMSA/Samples/Example_Usecases/05._Network_Orchestration/Alaxala/Process_Delete_Vlan/Tasks/Task_DELETE.php">
      <processPath/>
      <displayName>Remove VLAN</displayName>
    </task>
  </process>
</ObjectDefinition>
